crossfiledialog/__init__.py
crossfiledialog/exceptions.py
crossfiledialog/kdialog.py
crossfiledialog/osascript.py
crossfiledialog/strings.py
crossfiledialog/win32.py
crossfiledialog/wrapper.py
crossfiledialog/zenity.py
crossfiledialog-1.1.0.dist-info/licenses/LICENSE
crossfiledialog-1.1.0.dist-info/METADATA
crossfiledialog-1.1.0.dist-info/WHEEL
crossfiledialog-1.1.0.dist-info/top_level.txt
crossfiledialog-1.1.0.dist-info/RECORD
