Metadata-Version: 2.4
Name: crossfiledialog
Version: 1.1.0
Summary: A Python wrapper for opening files and folders with the native file dialog.
Home-page: https://github.com/maikelwever/crossfiledialog/
Author: Maikel Wever
Author-email: maikelwever@gmail.com
Classifier: Development Status :: 5 - Production/Stable
Classifier: Intended Audience :: Developers
Classifier: License :: OSI Approved :: GNU Lesser General Public License v3 (LGPLv3)
Classifier: Programming Language :: Python :: 3
Classifier: Environment :: X11 Applications :: GTK
Classifier: Environment :: X11 Applications :: KDE
Classifier: Environment :: Win32 (MS Windows)
Classifier: Operating System :: OS Independent
Classifier: Operating System :: Microsoft
Classifier: Operating System :: POSIX :: Linux
Classifier: Topic :: Desktop Environment :: File Managers
Requires-Python: >=3.4
License-File: LICENSE
Dynamic: author
Dynamic: author-email
Dynamic: classifier
Dynamic: description
Dynamic: description-content-type
Dynamic: home-page
Dynamic: license-file
Dynamic: requires-python
Dynamic: summary
